setup.py
BookingAnalysis/BookingData.py
BookingAnalysis/__init__.py
BookingAnalysis/rearrangements.py
BookingAnalysis.egg-info/PKG-INFO
BookingAnalysis.egg-info/SOURCES.txt
BookingAnalysis.egg-info/dependency_links.txt
BookingAnalysis.egg-info/not-zip-safe
BookingAnalysis.egg-info/top_level.txt