Metadata-Version: 1.0
Name: BookingAnalysis
Version: 0.0.1
Summary: Simplyfy operations with booking reservations related data
Home-page: UNKNOWN
Author: Martin Pons Martinez
Author-email: UNKNOWN
License: UNKNOWN
Platform: UNKNOWN
